pvorcademo/LICENSE
pvorcademo/orca_demo.py
pvorcademo/orca_demo_streaming.py
pvorcademo-2.0.0.dist-info/METADATA
pvorcademo-2.0.0.dist-info/WHEEL
pvorcademo-2.0.0.dist-info/entry_points.txt
pvorcademo-2.0.0.dist-info/top_level.txt
pvorcademo-2.0.0.dist-info/RECORD
